ftirfit/__init__.py
ftirfit/custom_funx.py
ftirfit/plot_utils.py
ftirfit-0.0.4.dist-info/LICENSE
ftirfit-0.0.4.dist-info/METADATA
ftirfit-0.0.4.dist-info/WHEEL
ftirfit-0.0.4.dist-info/top_level.txt
ftirfit-0.0.4.dist-info/RECORD
