Metadata-Version: 2.1
Name: ftirfit
Version: 0.0.4
Summary: Fitting FTIR data.
Author: Avratanu Biswas
Classifier: Programming Language :: Python :: 3
Classifier: License :: OSI Approved :: MIT License
Classifier: Operating System :: OS Independent
Requires-Python: >=3.6
License-File: LICENSE
Requires-Dist: rampy
Requires-Dist: matplotlib
Requires-Dist: pandas
Requires-Dist: scipy
Requires-Dist: numpy
Requires-Dist: lmfit
Requires-Dist: pybroom
